sxhkd_parser/__init__.py
sxhkd_parser/_package.py
sxhkd_parser/errors.py
sxhkd_parser/keysyms.py
sxhkd_parser/metadata.py
sxhkd_parser/parser.py
sxhkd_parser/util.py
sxhkd_parser/cli/__init__.py
sxhkd_parser/cli/common.py
sxhkd_parser/cli/hkcheck.py
sxhkd_parser/cli/hkdebug.py
sxhkd_parser/cli/hkexport.py
sxhkd_parser/cli/hkfind.py
sxhkd_parser/cli/hkwatch.py
sxhkd_parser/cli/hkxargs.py
sxhkd_parser-0.1.0.data/data/share/man/man1/hkcheck.1
sxhkd_parser-0.1.0.data/data/share/man/man1/hkdebug.1
sxhkd_parser-0.1.0.data/data/share/man/man1/hkexport.1
sxhkd_parser-0.1.0.data/data/share/man/man1/hkfind.1
sxhkd_parser-0.1.0.data/data/share/man/man1/hkwatch.1
sxhkd_parser-0.1.0.data/data/share/man/man1/hkxargs.1
sxhkd_parser-0.1.0.data/data/share/man/man7/sxhkd-parser.7
sxhkd_parser-0.1.0.dist-info/COPYING
sxhkd_parser-0.1.0.dist-info/METADATA
sxhkd_parser-0.1.0.dist-info/WHEEL
sxhkd_parser-0.1.0.dist-info/entry_points.txt
sxhkd_parser-0.1.0.dist-info/top_level.txt
sxhkd_parser-0.1.0.dist-info/RECORD
