Metadata-Version: 2.1
Name: sxhkd-parser
Version: 0.1.0
Summary: Library for parsing config files for sxhkd, and command-line programs using it
Home-page: https://github.com/Hoboneer/sxhkd-parser
Author: Gabriel Lisaca
Author-email: gabriel.lisaca@gmail.com
License: GPL-3.0-or-later
Keywords: hotkey,parser,sxhkd
Platform: POSIX
Platform: Linux
Classifier: Development Status :: 3 - Alpha
Classifier: Operating System :: POSIX
Classifier: Programming Language :: Python :: 3 :: Only
Classifier: Programming Language :: Python :: 3.7
Classifier: Programming Language :: Python :: 3.8
Classifier: Programming Language :: Python :: 3.9
Classifier: License :: OSI Approved :: GNU General Public License v3 or later (GPLv3+)
Classifier: License :: DFSG approved
Requires-Python: >=3.7
